MANIFEST.in
setup.cfg
setup.py
versioneer.py
environments/__init__.py
environments/_version.py
environments/environment.py
environments/prims.py
environments/tools.py
environments.egg-info/PKG-INFO
environments.egg-info/SOURCES.txt
environments.egg-info/dependency_links.txt
environments.egg-info/pbr.json
environments.egg-info/top_level.txt
environments/envs/__init__.py
environments/envs/collision2d.py
environments/envs/kinchain.py
environments/envs/kinscene.py
environments/envs/physicx.py
environments/envs/pusharray.py
environments/envs/square2d.py
environments/envs/vowel.py
environments/mprims/__init__.py
environments/mprims/dmp.py
environments/mprims/m_prims.py
test/test_collisions.py
test/test_envs.py
test/test_kin2d.py
test/test_mprims.py
test/test_physicx.py
test/test_pusharray.py