Metadata-Version: 1.1
Name: environments
Version: 1.0.1
Summary: Blackbox environment interface and implementations for autonomous exploration of sensorimotor spaces
Home-page: github.com/humm/environments.git
Author: Fabien Benureau
Author-email: fabien.benureau@inria.fr
License: Open Science License (see fabien.benureau.com/openscience.html)
Download-URL: https://github.com/humm/environments/tarball/1.0.1
Keywords: exploration algorithm blackbox
Platform: UNKNOWN
Classifier: Development Status :: 4 - Beta
Classifier: Programming Language :: Python :: 2.7
Classifier: Intended Audience :: Science/Research
Requires: scicfg
Requires: numpy
